imrepltool/__init__.py
imrepltool/imrepltool.py
imrepltool/save_img_array.py
imrepltool/set_logger.py
imrepltool/sqlite_model.py
imrepltool/sqlite_orm.py
imrepltool-0.1.5.dist-info/LICENSE
imrepltool-0.1.5.dist-info/METADATA
imrepltool-0.1.5.dist-info/WHEEL
imrepltool-0.1.5.dist-info/top_level.txt
imrepltool-0.1.5.dist-info/RECORD
