Metadata-Version: 2.1
Name: imrepltool
Version: 0.1.5
Summary: check the image contains the specified image template and set to cover it up
Home-page: https://github.com/GuardianGH/imrepltool/tree/master/imrepltool
Author: GuardianAngel
Author-email: zhling2012@live.com
License: UNKNOWN
Platform: UNKNOWN
Classifier: Programming Language :: Python :: 3
Classifier: License :: OSI Approved :: MIT License
Classifier: Operating System :: OS Independent
Requires-Dist: decorator (>=4.4.0)
Requires-Dist: imageio (>=2.5.0)
Requires-Dist: matplotlib (>=3.1.1)
Requires-Dist: numpy (>=1.17.0)
Requires-Dist: Pillow (>=6.1.0)
Requires-Dist: PyMySQL (>=0.9.3)
Requires-Dist: SQLAlchemy (>=1.3.7)
Requires-Dist: requests (>=2.22.0)
Requires-Dist: tqdm (>=4.32.1)
Requires-Dist: scikit-image (==0.15.0)
